observer_hooks/__init__.py
observer_hooks/block_events.py
observer_hooks/common.py
observer_hooks/decorators.py
observer_hooks/observer_hooks.py
observer_hooks-1.3.0.dist-info/LICENSE
observer_hooks-1.3.0.dist-info/METADATA
observer_hooks-1.3.0.dist-info/WHEEL
observer_hooks-1.3.0.dist-info/top_level.txt
observer_hooks-1.3.0.dist-info/RECORD
