Metadata-Version: 2.1
Name: observer-hooks
Version: 1.3.0
Summary: Easy, minimalist tools for function side-effects and observer pattern with weak references
Home-page: https://github.com/ILikesCaviar/ObserverHooks
Author: Ryan McConnell
Classifier: Programming Language :: Python :: 3
Classifier: License :: OSI Approved :: MIT License
Classifier: Operating System :: OS Independent
Requires-Python: >=3.0
License-File: LICENSE
Requires-Dist: ordered-set (>=4.1.0)
